sysinformer/__init__.py
sysinformer/config/__init__.py
sysinformer/config/config_parser.py
sysinformer/config/default_config.py
sysinformer/constants.py
sysinformer/core/__init__.py
sysinformer/core/containers.py
sysinformer/core/cpu.py
sysinformer/core/disks.py
sysinformer/core/latency.py
sysinformer/core/memory.py
sysinformer/core/networking.py
sysinformer/core/processes.py
sysinformer/core/services.py
sysinformer/core/system.py
sysinformer/main.py
sysinformer/utilities/__init__.py
sysinformer/utilities/exceptions.py
sysinformer/utilities/utils.py
python_sysinformer-1.10.1.dist-info/LICENSE
python_sysinformer-1.10.1.dist-info/METADATA
python_sysinformer-1.10.1.dist-info/WHEEL
python_sysinformer-1.10.1.dist-info/entry_points.txt
python_sysinformer-1.10.1.dist-info/RECORD
