Metadata-Version: 2.1
Name: python-sysinformer
Version: 1.10.1
Summary: A simple system information tool for Linux
Author: Timothy Bryant
Author-email: timothybryant3@gmail.com
Requires-Python: >=3.9
Classifier: Programming Language :: Python :: 3
Classifier: Programming Language :: Python :: 3.9
Classifier: Programming Language :: Python :: 3.10
Classifier: Programming Language :: Python :: 3.11
Requires-Dist: click (>=8.1.7,<9.0.0)
Requires-Dist: distro (>=1.8.0,<2.0.0)
Requires-Dist: netifaces (>=0.11.0,<0.12.0)
Requires-Dist: ping3 (>=4.0.4,<5.0.0)
Requires-Dist: psutil (>=5.9.5,<6.0.0)
Requires-Dist: pyyaml (>=6.0.1,<7.0.0)
Requires-Dist: tabulate (>=0.9.0,<0.10.0)
